<?xml version="1.0" encoding="utf-8"?>
<!DOCTYPE hibernate-mapping PUBLIC "-//Hibernate/Hibernate Mapping DTD 3.0//EN"
"http://www.hibernate.org/dtd/hibernate-mapping-3.0.dtd">
<!-- 
    Mapping file autogenerated by MyEclipse Persistence Tools
-->
<hibernate-mapping>
    <class name="com.nuaa.ec.model.TfstudentCompetitionGuidanceScore" table="TFStudentCompetitionGuidance_Score" schema="dbo" catalog="ScientificResearch">
        <id name="scguidaceScoreId" type="java.lang.String">
            <column name="SCGuidaceScoreID" length="20" />
            <generator class="assigned" />
        </id>
        <many-to-one name="tfstudentCompetitionGuidanceCompetitionType" class="com.nuaa.ec.model.TfstudentCompetitionGuidanceCompetitionType" fetch="select">
            <column name="competitionTypeID" length="20" />
        </many-to-one>
        <many-to-one name="tfstudentCompetitionGuidanceRewardLevel" class="com.nuaa.ec.model.TfstudentCompetitionGuidanceRewardLevel" fetch="select">
            <column name="RewardLevelID" length="20" />
        </many-to-one>
        <property name="baseScore" type="java.lang.Double">
            <column name="BaseScore" precision="53" scale="0" />
        </property>
        <property name="spareTire" type="java.lang.String">
            <column name="SpareTire" length="20" />
        </property>
        <set name="tfstudentCompetitionGuidancePerformances" inverse="true">
            <key>
                <column name="SCGuidanceScoreID" length="20" />
            </key>
            <one-to-many class="com.nuaa.ec.model.TfstudentCompetitionGuidancePerformance" />
        </set>
    </class>
</hibernate-mapping>
